django_mapengine/__init__.py
django_mapengine/apps.py
django_mapengine/choropleth.py
django_mapengine/colorbrewer.py
django_mapengine/distill.py
django_mapengine/layers.py
django_mapengine/legend.py
django_mapengine/managers.py
django_mapengine/middleware.py
django_mapengine/mvt.py
django_mapengine/popups.py
django_mapengine/setup.py
django_mapengine/sources.py
django_mapengine/static/django_mapengine/css/legend.css
django_mapengine/static/django_mapengine/images/layer_ctrl_dark.svg
django_mapengine/static/django_mapengine/images/layer_ctrl_default.svg
django_mapengine/static/django_mapengine/images/layer_ctrl_light.svg
django_mapengine/static/django_mapengine/images/layer_ctrl_satellite.svg
django_mapengine/static/django_mapengine/js/basemaps.js
django_mapengine/static/django_mapengine/js/choropleth.js
django_mapengine/static/django_mapengine/js/events.js
django_mapengine/static/django_mapengine/js/helper.js
django_mapengine/static/django_mapengine/js/hover.js
django_mapengine/static/django_mapengine/js/init.js
django_mapengine/static/django_mapengine/js/layer.js
django_mapengine/static/django_mapengine/js/legend.js
django_mapengine/static/django_mapengine/js/map.js
django_mapengine/static/django_mapengine/js/popup.js
django_mapengine/static/django_mapengine/js/store.js
django_mapengine/templates/django_mapengine/legend.html
django_mapengine/templates/django_mapengine/legend_item.html
django_mapengine/templates/django_mapengine/map_basemaps.html
django_mapengine/templates/django_mapengine/map_js.html
django_mapengine/templates/django_mapengine/map_json.html
django_mapengine/urls.py
django_mapengine/utils.py
django_mapengine/views.py
django_mapengine-3.2.1.dist-info/METADATA
django_mapengine-3.2.1.dist-info/WHEEL
django_mapengine-3.2.1.dist-info/licenses/LICENSE
django_mapengine-3.2.1.dist-info/RECORD
