Metadata-Version: 2.4
Name: django-mapengine
Version: 3.2.1
Summary: Map engine for maplibre in django
License-File: LICENSE
Author: Hendrik Huyskens
Author-email: hendrik.huyskens@rl-institut.de
Requires-Python: >=3.9,<3.12
Classifier: Programming Language :: Python :: 3
Classifier: License :: OSI Approved :: MIT License
Classifier: Operating System :: OS Independent
Requires-Dist: django-appconf (>=1.0.5)
Requires-Dist: django-distill (>=3.1.3)
Requires-Dist: django-environ (>=0.10.0)
Requires-Dist: django-geojson (>=3.2.1)
Requires-Dist: djangorestframework (>=3.14.0)
Requires-Dist: djangorestframework-mvt (>=0.2.5)
Requires-Dist: range-key-dict (>=1.1.0)
Project-URL: Homepage, https://github.com/rl-institut/django-mapengine
Project-URL: Issues, https://github.com/rl-institut/django-mapengine/issues
